enforce/__init__.py
enforce/decorators.py
enforce/enforcers.py
enforce/exceptions.py
enforce/nodes.py
enforce/parsers.py
enforce/settings.py
enforce/types.py
enforce/utils.py
enforce/validator.py
enforce/validators.py
enforce/wrappers.py
enforce-0.3.3.dist-info/DESCRIPTION.rst
enforce-0.3.3.dist-info/METADATA
enforce-0.3.3.dist-info/RECORD
enforce-0.3.3.dist-info/WHEEL
enforce-0.3.3.dist-info/metadata.json
enforce-0.3.3.dist-info/top_level.txt
