Metadata-Version: 2.0
Name: enforce
Version: 0.3.3
Summary: Python 3.5+ library for integration testing and data validation through configurable and optional runtime type hint enforcement.
Home-page: https://github.com/RussBaz/enforce
Author: RussBaz
Author-email: RussBaz@users.noreply.github.com
License: MIT
Requires-Dist: wrapt
